mkdocs_abs_rel_plugin/__init__.py
mkdocs_abs_rel_plugin/plugin.py
mkdocs_abs_rel_plugin-0.2.4.dist-info/METADATA
mkdocs_abs_rel_plugin-0.2.4.dist-info/WHEEL
mkdocs_abs_rel_plugin-0.2.4.dist-info/entry_points.txt
mkdocs_abs_rel_plugin-0.2.4.dist-info/top_level.txt
mkdocs_abs_rel_plugin-0.2.4.dist-info/RECORD
