Metadata-Version: 2.1
Name: mkdocs-abs-rel-plugin
Version: 0.2.4
Summary: Mkdocs plugin to convert absolute paths to relative ones.
Home-page: https://github.com/sander76/mkdocs-abs-rel-plugin
Author: sander
Author-email: 
License: MIT
Platform: UNKNOWN
